openjd/model/__init__.py
openjd/model/_capabilities.py
openjd/model/_convert_pydantic_error.py
openjd/model/_create_job.py
openjd/model/_errors.py
openjd/model/_merge_job_parameter.py
openjd/model/_parse.py
openjd/model/_range_expr.py
openjd/model/_step_dependency_graph.py
openjd/model/_step_param_space_iter.py
openjd/model/_symbol_table.py
openjd/model/_tokenstream.py
openjd/model/_types.py
openjd/model/_version.py
openjd/model/py.typed
openjd/model/_format_strings/__init__.py
openjd/model/_format_strings/_dyn_constrained_str.py
openjd/model/_format_strings/_edit_distance.py
openjd/model/_format_strings/_expression.py
openjd/model/_format_strings/_format_string.py
openjd/model/_format_strings/_nodes.py
openjd/model/_format_strings/_parser.py
openjd/model/_format_strings/_tokens.py
openjd/model/_internal/__init__.py
openjd/model/_internal/_combination_expr.py
openjd/model/_internal/_create_job.py
openjd/model/_internal/_param_space_dim_validation.py
openjd/model/_internal/_validator_functions.py
openjd/model/_internal/_variable_reference_validation.py
openjd/model/v2023_09/__init__.py
openjd/model/v2023_09/_model.py
openjd_model-0.8.7.dist-info/METADATA
openjd_model-0.8.7.dist-info/WHEEL
openjd_model-0.8.7.dist-info/licenses/LICENSE
openjd_model-0.8.7.dist-info/licenses/NOTICE
openjd_model-0.8.7.dist-info/RECORD
