Metadata-Version: 2.4
Name: openjd-model
Version: 0.8.7
Summary: Provides a Python implementation of the data model for Open Job Description's template schemas.
Project-URL: Homepage, https://github.com/OpenJobDescription/openjd-model-for-python
Project-URL: Source, https://github.com/OpenJobDescription/openjd-model-for-python
Author: Amazon Web Services
License-Expression: Apache-2.0
License-File: LICENSE
License-File: NOTICE
Classifier: Development Status :: 5 - Production/Stable
Classifier: Intended Audience :: Developers
Classifier: License :: OSI Approved :: Apache Software License
Classifier: Operating System :: MacOS
Classifier: Operating System :: Microsoft :: Windows
Classifier: Operating System :: POSIX :: Linux
Classifier: Programming Language :: Python
Classifier: Programming Language :: Python :: 3 :: Only
Classifier: Programming Language :: Python :: 3.9
Classifier: Programming Language :: Python :: 3.10
Classifier: Programming Language :: Python :: 3.11
Classifier: Programming Language :: Python :: 3.12
Classifier: Topic :: Software Development :: Libraries
Requires-Python: >=3.9
Requires-Dist: pydantic<3,>=2.10
Requires-Dist: pyyaml==6.0.*
